qudi_hira_analysis/__init__.py
qudi_hira_analysis/_fitmethods/__init__.py
qudi_hira_analysis/_fitmethods/antibunchingmethods.py
qudi_hira_analysis/_fitmethods/decaylikemethods.py
qudi_hira_analysis/_fitmethods/gaussianlikemethods.py
qudi_hira_analysis/_fitmethods/generalmethods.py
qudi_hira_analysis/_fitmethods/hyperbolicsaturationmethods.py
qudi_hira_analysis/_fitmethods/linearmethods.py
qudi_hira_analysis/_fitmethods/lorentzianlikemethods.py
qudi_hira_analysis/_fitmethods/poissonianlikemethods.py
qudi_hira_analysis/_fitmethods/sinemethods.py
qudi_hira_analysis/_qudi_fit_logic.py
qudi_hira_analysis/_raster_odmr_fitting.py
qudi_hira_analysis/_version.py
qudi_hira_analysis/analysis_logic.py
qudi_hira_analysis/data_handler.py
qudi_hira_analysis/helper_functions.py
qudi_hira_analysis/io_handler.py
qudi_hira_analysis/measurement_dataclass.py
qudi_hira_analysis-1.6.3.dist-info/LICENSE
qudi_hira_analysis-1.6.3.dist-info/METADATA
qudi_hira_analysis-1.6.3.dist-info/WHEEL
qudi_hira_analysis-1.6.3.dist-info/RECORD
