Metadata-Version: 2.1
Name: qudi-hira-analysis
Version: 1.6.3
Summary: A Python toolkit to analzye photon timetrace data from qubit sensors
Home-page: https://github.com/dineshpinto/qudi-hira-analysis
License: Apache-2.0
Keywords: python,qubit,analysis,nv centers,photon timetrace
Author: dineshpinto
Author-email: annual.fallout_0z@icloud.com
Requires-Python: >=3.10,<3.13
Classifier: License :: OSI Approved :: Apache Software License
Classifier: Programming Language :: Python :: 3
Classifier: Programming Language :: Python :: 3.10
Classifier: Programming Language :: Python :: 3.11
Classifier: Programming Language :: Python :: 3.12
Requires-Dist: lmfit (>=1.1.0,<2.0.0)
Requires-Dist: matplotlib (>=3.8.2,<4.0.0)
Requires-Dist: numpy (>=1.26.0,<2.0.0)
Requires-Dist: openpyxl (>=3.0.10,<4.0.0)
Requires-Dist: pandas (>=2.0.0,<3.0.0)
Requires-Dist: pyspm (>=0.6.0,<0.7.0)
Requires-Dist: tqdm (>=4.64.1,<5.0.0)
Requires-Dist: xlrd (>=2.0.1,<3.0.0)
Project-URL: Documentation, https://dineshpinto.github.io/qudi-hira-analysis/qudi_hira_analysis/
Project-URL: Repository, https://github.com/dineshpinto/qudi-hira-analysis
